mdbttack/__init__.py
mdbttack/mdbttack.py
mdbttack-0.0.1.dist-info/LICENSE
mdbttack-0.0.1.dist-info/METADATA
mdbttack-0.0.1.dist-info/WHEEL
mdbttack-0.0.1.dist-info/entry_points.txt
mdbttack-0.0.1.dist-info/top_level.txt
mdbttack-0.0.1.dist-info/RECORD
