Metadata-Version: 2.1
Name: mdbttack
Version: 0.0.1
Summary: mdbttack
Home-page: https://github.com/Nathalon/mdbttack.git
Author: Nathalon
License: GPL v3
Platform: UNKNOWN
License-File: LICENSE
